torchsight/__init__.py
torchsight-0.0.1.dist-info/LICENSE
torchsight-0.0.1.dist-info/METADATA
torchsight-0.0.1.dist-info/WHEEL
torchsight-0.0.1.dist-info/top_level.txt
torchsight-0.0.1.dist-info/RECORD
